{
    "Grid": 
    {
        "mission": "install a printer",
        "auto": {
            "room_split_dirs": ["vert", "horz"],
            "min_room_dim": 1,
            "max_num_room": 4
        },
        "width": 12,
        "height": 12,
        "agents":
        {
            "pos": null,
            "dir": null
        },
        "rooms":
        {
            "num": 2,
            "initial":
            [
                {
                    "top": [1, 1],
                    "size": [5, 10],
                    "furnitures": 
                    {
                        "num": 2,
                        "initial": 
                        [
                            {
                                "type": "printer",
                                "state": [["toggleable", 0]],
                                "pos": [2, 2],
                                "objs": null
                            },
                            {
                                "type": "table",
                                "state": null,
                                "pos": null,
                                "objs": {
                                    "num": 1,
                                    "initial": 
                                    [
                                        {
                                            "type": "book",
                                            "state": [["dustyable", 1]],
                                            "pos": null
                                        }
                                    ]
                                }
                            }
                        ]
                    }
                },
                {
                    "top": [7, 1],
                    "size": [4, 10],
                    "furnitures": 
                    {
                        "num": 2,
                        "initial": 
                        [
                            {
                                "type": "printer",
                                "state": [["toggleable", 0]],
                                "pos": null,
                                "objs": null
                            },
                            {
                                "type": "box",
                                "state": null,
                                "pos": null,
                                "objs": null
                            }
                        ]
                    }
                }
            ]
        }
    }
}